AUTHORS
LICENSE
MANIFEST.in
README.rst
setup.py
django_o2o_tagging.egg-info/PKG-INFO
django_o2o_tagging.egg-info/SOURCES.txt
django_o2o_tagging.egg-info/dependency_links.txt
django_o2o_tagging.egg-info/not-zip-safe
django_o2o_tagging.egg-info/requires.txt
django_o2o_tagging.egg-info/top_level.txt
o2o_tagging/__init__.py
o2o_tagging/forms.py
o2o_tagging/managers.py
o2o_tagging/models.py
o2o_tagging/signals.py
o2o_tagging/urls.py
o2o_tagging/views.py
o2o_tagging/templatetags/__init__.py
o2o_tagging/templatetags/o2o_tagging.py
o2o_tagging/tests/__init__.py
o2o_tagging/tests/models.py
o2o_tagging/tests/tests_forms.py
o2o_tagging/tests/tests_models.py
o2o_tagging/tests/tests_templatetags.py
o2o_tagging/tests/tests_views.py