Metadata-Version: 1.0
Name: django-o2o-tagging
Version: 0.2.2
Summary: Use this app to tag objects like you tag your friends on facebook, but using any objects as the tagger and the tagged. Think of a `User` tagging a `Friend` in a `Photo` all of them being different models.
Home-page: https://github.com/alej0varas/django-o2o_tagging
Author: Alejandro Varas
Author-email: alej0varas@gmail.com
License: GNU General Public License
Platform: UNKNOWN
Classifier: Topic :: Internet :: WWW/HTTP :: Dynamic Content
Classifier: Intended Audience :: Developers
Classifier: Programming Language :: Python
Classifier: Programming Language :: Python :: 2.6
Classifier: Framework :: Django
Classifier: Development Status :: 4 - Beta
Classifier: Operating System :: OS Independent
